Workbook
Name aporte: #REF!
Name Axis14_taxa: INVESTIMENTO!$G$16
Name investimento_30: INVESTIMENTO!$G$22
Name patrimonio: #REF!
Name qtd_anos: #REF!
Name Rendimento_Carteira: INVESTIMENTO!$G$21
Name salario: INVESTIMENTO!$G$20
Name taxa_mensal: #REF!

Sheet INVESTIMENTO
E15: AXIS14 cotação | G15: AXIS14 taxa
E16: 5 | G16: 0.01079
E19: INVESTIMENTO MENSAL
E20: Salário | G20: 5000
E21: taxa de Rendimento Carteira | G21: =Axis14_taxa -> 0.01079
E22: Sugestão de Investimento (30%) | G22: =salario*30% -> 1500
E26: INVESTIMENTO MENSAL
E27: Quanto investir por mês ? | G27: 1260
D28: 2 | E28: Por Quantos Anos ? | G28: 5
D29: 5 | E29: Taxa de Rendimento mensal ? | G29: =Axis14_taxa -> 0.01079
D30: 10 | E30: Patrimônio acumulado ? | G30: =FV(G29,G28*12,G27*-1) -> 105558.91
D31: 20 | E31: Dividendos Mensais ? | G31: =G30*G29 -> 1138.9807
D32: 30 | E32: cotas adquiridas ? | G32: =G30/E16 -> 21111.782
E35: Cenários Patrimônio | H35: Dividendo
E36: Quanto em 2 Anos ? | G36: =FV($G$29,$D28*12,$G$27*-1) -> 34306.81 | H36: =G36*$G$29 -> 370.17048
E37: Quanto em 5 Anos ? | G37: =FV($G$29,$D29*12,$G$27*-1) -> 105558.91 | H37: =G37*$G$29 -> 1138.9807
E38: Quanto em 10 Anos ? | G38: =FV($G$29,$D30*12,$G$27*-1) -> 306538.11 | H38: =G38*$G$29 -> 3307.5462
E39: Quanto em 20 Anos ? | G39: =FV($G$29,$D31*12,$G$27*-1) -> 1417750 | H39: =G39*$G$29 -> 15297.522
E40: Quanto em 30 Anos ? | G40: =FV($G$29,$D32*12,$G$27*-1) -> 5445933.8 | H40: =G40*$G$29 -> 58761.625
E43: Perfil | H43: moderado
E44: VALOR A SER INVESTIDO POR MÊS | H44: =G27 -> 1260
E46: tipo de FII | G46: percentual Sugerido | H46: valores
E47: PAPEL | G47: =VLOOKUP($H$43&"-"&E47,'ideias '!$A$1:$D$20,4,FALSE) -> 0.32 | H47: =$H$44*G47 -> 403.2
E48: TIJOLO | G48: =VLOOKUP($H$43&"-"&E48,'ideias '!$A$1:$D$20,4,FALSE) -> 0.35 | H48: =$H$44*G48 -> 441
E49: HÍBRIDOS | G49: =VLOOKUP($H$43&"-"&E49,'ideias '!$A$1:$D$20,4,FALSE) -> 0.08 | H49: =$H$44*G49 -> 100.8
E50: FOFs | G50: =VLOOKUP($H$43&"-"&E50,'ideias '!$A$1:$D$20,4,FALSE) -> 0.05 | H50: =$H$44*G50 -> 63
E51: DESENVOLVIMENTO | G51: =VLOOKUP($H$43&"-"&E51,'ideias '!$A$1:$D$20,4,FALSE) -> 0.1 | H51: =$H$44*G51 -> 126
E52: HOTELARIAS | G52: =VLOOKUP($H$43&"-"&E52,'ideias '!$A$1:$D$20,4,FALSE) -> 0.1 | H52: =$H$44*G52 -> 126
H53: =SUM(H47:H52) -> 1260

Sheet ideias 
A2: CHAVE | B2: PERFIL | C2: TIPO DE FII | D2: %
A3: =B3&"-"&C3 -> Conservador-PAPEL | B3: Conservador | C3: PAPEL | D3: 0.3
A4: =B4&"-"&C4 -> Conservador-TIJOLO | B4: Conservador | C4: TIJOLO | D4: 0.5
A5: =B5&"-"&C5 -> Conservador-HÍBRIDOS | B5: Conservador | C5: HÍBRIDOS | D5: 0.1
A6: =B6&"-"&C6 -> Conservador-FOFs | B6: Conservador | C6: FOFs | D6: 0.1
A7: =B7&"-"&C7 -> Conservador-DESENVOLVIMENTO | B7: Conservador | C7: DESENVOLVIMENTO | D7: 0
A8: =B8&"-"&C8 -> Conservador-HOTELARIAS | B8: Conservador | C8: HOTELARIAS | D8: 0
A9: =B9&"-"&C9 -> Moderado-PAPEL | B9: Moderado | C9: PAPEL | D9: 0.32
A10: =B10&"-"&C10 -> Moderado-TIJOLO | B10: Moderado | C10: TIJOLO | D10: 0.35
A11: =B11&"-"&C11 -> Moderado-HÍBRIDOS | B11: Moderado | C11: HÍBRIDOS | D11: 0.08
A12: =B12&"-"&C12 -> Moderado-FOFs | B12: Moderado | C12: FOFs | D12: 0.05
A13: =B13&"-"&C13 -> Moderado-DESENVOLVIMENTO | B13: Moderado | C13: DESENVOLVIMENTO | D13: 0.1
A14: =B14&"-"&C14 -> Moderado-HOTELARIAS | B14: Moderado | C14: HOTELARIAS | D14: 0.1
... A20: =B20&"-"&C20 -> Agressivo-HOTELARIAS | B20: Agressivo | C20: HOTELARIAS | D20: 0.1
